ntucool/__base_old.py
ntucool/__init__.py
ntucool/auth.py
ntucool/base.py
ntucool/course.py
ntucool/descriptor.py
ntucool/main.py
ntucool/requestor.py
ntucool/utils.py
ntucool/canvasapi/__init__.py
ntucool/canvasapi/canvasapi.py
ntucool/canvasapi/_canvasapi/__init__.py
ntucool/canvasapi/_canvasapi/account.py
ntucool/canvasapi/_canvasapi/account_calendar.py
ntucool/canvasapi/_canvasapi/appointment_group.py
ntucool/canvasapi/_canvasapi/assignment.py
ntucool/canvasapi/_canvasapi/authentication_event.py
ntucool/canvasapi/_canvasapi/authentication_provider.py
ntucool/canvasapi/_canvasapi/avatar.py
ntucool/canvasapi/_canvasapi/blueprint.py
ntucool/canvasapi/_canvasapi/bookmark.py
ntucool/canvasapi/_canvasapi/calendar_event.py
ntucool/canvasapi/_canvasapi/canvas.py
ntucool/canvasapi/_canvasapi/canvas_object.py
ntucool/canvasapi/_canvasapi/collaboration.py
ntucool/canvasapi/_canvasapi/comm_message.py
ntucool/canvasapi/_canvasapi/communication_channel.py
ntucool/canvasapi/_canvasapi/content_export.py
ntucool/canvasapi/_canvasapi/content_migration.py
ntucool/canvasapi/_canvasapi/conversation.py
ntucool/canvasapi/_canvasapi/course.py
ntucool/canvasapi/_canvasapi/course_epub_export.py
ntucool/canvasapi/_canvasapi/course_event.py
ntucool/canvasapi/_canvasapi/current_user.py
ntucool/canvasapi/_canvasapi/custom_gradebook_columns.py
ntucool/canvasapi/_canvasapi/discussion_topic.py
ntucool/canvasapi/_canvasapi/enrollment.py
ntucool/canvasapi/_canvasapi/enrollment_term.py
ntucool/canvasapi/_canvasapi/eportfolio.py
ntucool/canvasapi/_canvasapi/exceptions.py
ntucool/canvasapi/_canvasapi/external_feed.py
ntucool/canvasapi/_canvasapi/external_tool.py
ntucool/canvasapi/_canvasapi/favorite.py
ntucool/canvasapi/_canvasapi/feature.py
ntucool/canvasapi/_canvasapi/file.py
ntucool/canvasapi/_canvasapi/folder.py
ntucool/canvasapi/_canvasapi/grade_change_log.py
ntucool/canvasapi/_canvasapi/gradebook_history.py
ntucool/canvasapi/_canvasapi/grading_period.py
ntucool-0.1.4.dist-info/METADATA
ntucool-0.1.4.dist-info/WHEEL
ntucool-0.1.4.dist-info/RECORD
