Metadata-Version: 2.3
Name: ntucool
Version: 0.1.4
Summary: Default template for PDM package
Author-email: kc0506 <kchong0506@gmail.com>
License: MIT
Requires-Python: >=3.12
Requires-Dist: aiofiles==23.2.1; python_version >= '3.7'
Requires-Dist: annotated-types==0.6.0; python_version >= '3.8'
Requires-Dist: anyio==4.3.0; python_version >= '3.8'
Requires-Dist: async-property>=0.2.2
Requires-Dist: attrs==23.2.0; python_version >= '3.7'
Requires-Dist: awaitlet>=0.0.1
Requires-Dist: beautifulsoup4==4.12.3; python_full_version >= '3.6.0'
Requires-Dist: canvasapi>=3.3.0
Requires-Dist: certifi==2024.2.2; python_version >= '3.6'
Requires-Dist: charset-normalizer==3.3.2; python_full_version >= '3.7.0'
Requires-Dist: click-spinner==0.1.10
Requires-Dist: click==8.1.7; python_version >= '3.7'
Requires-Dist: colorama==0.4.6; python_version >= '2.7' and python_version not in '3.0, 3.1, 3.2, 3.3, 3.4, 3.5, 3.6'
Requires-Dist: croniter==1.4.1; python_version >= '2.6' and python_version not in '3.0, 3.1, 3.2, 3.3'
Requires-Dist: datamodel-code-generator>=0.25.9
Requires-Dist: decorator==5.1.1; python_version >= '3.5'
Requires-Dist: dnspython==2.6.1; python_version >= '3.8'
Requires-Dist: docstring-parser>=0.16
Requires-Dist: email-validator==2.1.1; python_version >= '3.8'
Requires-Dist: executing>=2.0.1
Requires-Dist: greenback==1.2.1; python_version >= '3.8'
Requires-Dist: greenlet==3.0.3; python_version >= '3.7'
Requires-Dist: h11==0.14.0; python_version >= '3.7'
Requires-Dist: httpcore==1.0.5; python_version >= '3.8'
Requires-Dist: httptools==0.6.1
Requires-Dist: httpx==0.27.0; python_version >= '3.8'
Requires-Dist: idna==3.7; python_version >= '3.5'
Requires-Dist: iniconfig==2.0.0; python_version >= '3.7'
Requires-Dist: jinja2==3.1.4; python_version >= '3.7'
Requires-Dist: markdown-it-py==3.0.0; python_version >= '3.8'
Requires-Dist: markupsafe==2.1.5; python_version >= '3.7'
Requires-Dist: mdurl==0.1.2; python_version >= '3.7'
Requires-Dist: nest-asyncio==1.6.0; python_version >= '3.5'
Requires-Dist: numpy==1.26.4; python_version >= '3.9'
Requires-Dist: orjson==3.10.3; python_version >= '3.8'
Requires-Dist: outcome==1.3.0.post0; python_version >= '3.7'
Requires-Dist: packaging==24.0; python_version >= '3.7'
Requires-Dist: pluggy==1.5.0; python_version >= '3.8'
Requires-Dist: psutil==5.9.8; python_version >= '2.7' and python_version not in '3.0, 3.1, 3.2, 3.3, 3.4, 3.5'
Requires-Dist: pygments==2.18.0; python_version >= '3.8'
Requires-Dist: pyte==0.8.2; python_version >= '3.8'
Requires-Dist: pytest==8.2.0; python_version >= '3.8'
Requires-Dist: python-dateutil==2.9.0.post0; python_version >= '2.7' and python_version not in '3.0, 3.1, 3.2, 3.3'
Requires-Dist: python-dotenv==1.0.1; python_version >= '3.8'
Requires-Dist: python-multipart==0.0.9; python_version >= '3.8'
Requires-Dist: pyyaml==6.0.1
Requires-Dist: requests==2.31.0; python_version >= '3.7'
Requires-Dist: rich==13.7.1; python_full_version >= '3.7.0'
Requires-Dist: shellingham==1.5.4; python_version >= '3.7'
Requires-Dist: six==1.16.0; python_version >= '2.7' and python_version not in '3.0, 3.1, 3.2, 3.3'
Requires-Dist: sniffio==1.3.1; python_version >= '3.7'
Requires-Dist: soupsieve==2.5; python_version >= '3.8'
Requires-Dist: starlette==0.37.2; python_version >= '3.8'
Requires-Dist: thefuck==3.32
Requires-Dist: tqdm==4.66.4; python_version >= '3.7'
Requires-Dist: trio>=0.26.2
Requires-Dist: typer==0.12.3; python_version >= '3.7'
Requires-Dist: typing-extensions==4.11.0; python_version >= '3.8'
Requires-Dist: ujson==5.10.0; python_version >= '3.8'
Requires-Dist: urllib3==2.2.1; python_version >= '3.8'
Requires-Dist: watchfiles==0.21.0
Requires-Dist: wcwidth==0.2.13
Requires-Dist: websockets==12.0
Requires-Dist: win-unicode-console==0.5; sys_platform == 'win32'
